web_scraper_dmeurer/__init__.py
web_scraper_dmeurer-1.0.1.dist-info/METADATA
web_scraper_dmeurer-1.0.1.dist-info/WHEEL
web_scraper_dmeurer-1.0.1.dist-info/licenses/LICENSE
web_scraper_dmeurer-1.0.1.dist-info/RECORD
