Metadata-Version: 2.3
Name: web_scraper_dmeurer
Version: 1.0.1
Summary: A web scraper, that can scrape articles from a recursive website navigation
Project-URL: Homepage, https://github.com/DMeurer/web_scraper
Project-URL: Issues, https://github.com/DMeurer/web_scraper/issues
Author-email: Dominik Meurer <dom.meurer@gmx.de>
License-File: LICENSE
Classifier: License :: OSI Approved :: MIT License
Classifier: Operating System :: OS Independent
Classifier: Programming Language :: Python :: 3
Requires-Python: >=3.8
